setup.cfg
setup.py
bin/jarvis
jarvis/__init__.py
jarvis/ecs.py
jarvis/jarvis.py
jarvis_helper.egg-info/PKG-INFO
jarvis_helper.egg-info/SOURCES.txt
jarvis_helper.egg-info/dependency_links.txt
jarvis_helper.egg-info/not-zip-safe
jarvis_helper.egg-info/requires.txt
jarvis_helper.egg-info/top_level.txt