Metadata-Version: 1.1
Name: jarvis-helper
Version: 1.0.1
Summary: Ops management system --- JARVIS
Home-page: https://github.com/liozzazhang/JARVIS
Author: ZhangLei
Author-email: zlprasy@gmail.com
License: UNKNOWN
Keywords: automation,management
Platform: UNKNOWN
Classifier: Development Status :: 5 - Production/Stable
Classifier: License :: OSI Approved :: MIT License
Classifier: Programming Language :: Python :: 2.7
Classifier: Topic :: Software Development :: Libraries :: Application Frameworks
